iterlib/__init__.py
iterlib/common.py
iterlib/map.py
iterlib/preloader.py
iterlib-1.1.6.dist-info/LICENSE
iterlib-1.1.6.dist-info/METADATA
iterlib-1.1.6.dist-info/WHEEL
iterlib-1.1.6.dist-info/top_level.txt
iterlib-1.1.6.dist-info/RECORD
